yamal/__init__.py
yamal/sys_base.pyi
yamal/sys_base.so
yamal/testmodule.so
yamal/yamal8.pyi
yamal/yamal8.so
yamal/ytp.pyi
yamal/ytp.so
yamal/include/fmc/python/common.h
yamal/include/fmc++/python/component.hpp
yamal/include/fmc++/python/config.hpp
yamal/include/fmc++/python/wrapper.hpp
yamal/include/ytp/python/py_api.h
yamal/include/ytp/python/py_wrapper.h
yamal/tests/__init__.py
yamal/tests/sys_tests.py
yamal/tests/ytp.py
yamal/tests/ytp8.py
yamal-8.0.33.data/scripts/test-yamal-python
yamal-8.0.33.data/scripts/yamal-run.py
yamal-8.0.33.dist-info/LICENSE
yamal-8.0.33.dist-info/METADATA
yamal-8.0.33.dist-info/WHEEL
yamal-8.0.33.dist-info/top_level.txt
yamal-8.0.33.dist-info/RECORD
