Metadata-Version: 2.1
Name: yamal
Version: 8.0.33
Summary: Featuremine YTP packages
Home-page: https://www.featuremine.com
Author: Featuremine Corporation
Author-email: support@featuremine.com
License: COPYRIGHT (c) 2019-2023 by Featuremine Corporation
Classifier: Programming Language :: Python :: 3 :: Only
License-File: LICENSE
